[
  {
    "thumbnail_url": "https://i.pinimg.com/236x/03/af/69/03af69ffa3e496dc5532a38aa927d475.jpg",
    "pin_url": "https://kr.pinterest.com/pin/6051780745008382/"
  },
  {
    "thumbnail_url": "https://i.pinimg.com/236x/3c/e4/55/3ce4555687e8e085dce6145386fb88c9.jpg",
    "pin_url": "https://kr.pinterest.com/pin/5840674510236716/"
  },
  {
    "thumbnail_url": "https://i.pinimg.com/236x/aa/2b/98/aa2b986c52fbaec1999c215d9c9984b3.jpg",
    "pin_url": "https://kr.pinterest.com/pin/31314159904193172/"
  },
  {
    "thumbnail_url": "https://i.pinimg.com/236x/fa/1f/6b/fa1f6b6df366eb6d17b67d135cb9dbcc.jpg",
    "pin_url": "https://kr.pinterest.com/pin/914862418683124/"
  },
  {
    "thumbnail_url": "https://i.pinimg.com/236x/2b/2f/cf/2b2fcff43cdef85a1cd04f40e91e8174.jpg",
    "pin_url": "https://kr.pinterest.com/pin/3025924737172840/"
  },
  {
    "thumbnail_url": "https://i.pinimg.com/236x/a2/b7/19/a2b719e3a0d187867dd23b8501e53442.jpg",
    "pin_url": "https://kr.pinterest.com/pin/5136987064366927/"
  },
  {
    "thumbnail_url": "https://i.pinimg.com/236x/28/7a/ad/287aadd4a1302ad39ac76b3fec454438.jpg",
    "pin_url": "https://kr.pinterest.com/pin/422281205502977/"
  },
  {
    "thumbnail_url": "https://i.pinimg.com/236x/08/fd/3f/08fd3f5b12d1e4babcd51415149d39d6.jpg",
    "pin_url": "https://kr.pinterest.com/pin/908953137857720896/"
  },
  {
    "thumbnail_url": "https://i.pinimg.com/236x/6d/b3/73/6db37385903f982e98d830729d44900a.jpg",
    "pin_url": "https://kr.pinterest.com/pin/1548181126042386/"
  },
  {
    "thumbnail_url": "https://i.pinimg.com/236x/1f/57/c6/1f57c6b308a460547e46b875fca7f65a.jpg",
    "pin_url": "https://kr.pinterest.com/pin/176484879142612160/"
  },
  {
    "thumbnail_url": "https://i.pinimg.com/236x/e0/41/f4/e041f448f3f2a46a25a502d06ba7befc.jpg",
    "pin_url": "https://kr.pinterest.com/pin/382524562121316860/"
  },
  {
    "thumbnail_url": "https://i.pinimg.com/236x/f9/69/d2/f969d2e4db24e9e8049f8f5a1a5dd04e.jpg",
    "pin_url": "https://kr.pinterest.com/pin/1407443627216591/"
  },
  {
    "thumbnail_url": "https://i.pinimg.com/236x/1e/a2/1f/1ea21f07b216950c79f29ec69388f314.jpg",
    "pin_url": "https://kr.pinterest.com/pin/1125968651659238/"
  },
  {
    "thumbnail_url": "https://i.pinimg.com/236x/a6/8c/9c/a68c9c1ba5b6501220ebb611a653e093.jpg",
    "pin_url": "https://kr.pinterest.com/pin/46091596180805001/"
  },
  {
    "thumbnail_url": "https://i.pinimg.com/236x/42/c8/ee/42c8ee13c6aaae1867f30620073f5d32.jpg",
    "pin_url": "https://kr.pinterest.com/pin/36591815717925673/"
  },
  {
    "thumbnail_url": "https://i.pinimg.com/236x/95/4d/97/954d97097205bcc1bb872889819928eb.jpg",
    "pin_url": "https://kr.pinterest.com/pin/1900024835203269/"
  }
]