[
  {
    "thumbnail_url": "https://i.pinimg.com/236x/b5/15/82/b51582ed8d961511f95f2622480e313e.jpg",
    "pin_url": "https://kr.pinterest.com/pin/20547742045575555/"
  },
  {
    "thumbnail_url": "https://i.pinimg.com/236x/07/43/6e/07436ed6f9520458fc100fafbe8a0f53.jpg",
    "pin_url": "https://kr.pinterest.com/pin/1407443628563107/"
  },
  {
    "thumbnail_url": "https://i.pinimg.com/236x/43/03/a1/4303a13a5fffb43218fbb0d59edf80ce.jpg",
    "pin_url": "https://kr.pinterest.com/pin/153685406028772935/"
  },
  {
    "thumbnail_url": "https://i.pinimg.com/236x/bd/90/11/bd9011ab2a9284e1b0ff1ce07f4275c2.jpg",
    "pin_url": "https://kr.pinterest.com/pin/5348093303582845/"
  },
  {
    "thumbnail_url": "https://i.pinimg.com/236x/40/59/16/4059166ffb81f563431f95d77d666f54.jpg",
    "pin_url": "https://kr.pinterest.com/pin/155303888003453731/"
  },
  {
    "thumbnail_url": "https://i.pinimg.com/236x/0f/85/00/0f85001ed71df2a3b01a12621900b9ad.jpg",
    "pin_url": "https://kr.pinterest.com/pin/1759287343194348/"
  },
  {
    "thumbnail_url": "https://i.pinimg.com/236x/3c/99/4b/3c994b7cde2dbd4c717f42854a351508.jpg",
    "pin_url": "https://kr.pinterest.com/pin/2533343529759802/"
  },
  {
    "thumbnail_url": "https://i.pinimg.com/236x/ef/f5/20/eff520968346588666f74ddf63396c03.jpg",
    "pin_url": "https://kr.pinterest.com/pin/490610953143379589/"
  },
  {
    "thumbnail_url": "https://i.pinimg.com/236x/71/47/96/714796a01ae8aeeef4f21e58e126c4d6.jpg",
    "pin_url": "https://kr.pinterest.com/pin/60376451248408894/"
  },
  {
    "thumbnail_url": "https://i.pinimg.com/236x/02/2c/ac/022cac5030b3d76c7f0c5d30f9bb3254.jpg",
    "pin_url": "https://kr.pinterest.com/pin/422281211068619/"
  },
  {
    "thumbnail_url": "https://i.pinimg.com/236x/c5/2e/1b/c52e1bff2526e4355676a45326abf238.jpg",
    "pin_url": "https://kr.pinterest.com/pin/437060338858409548/"
  },
  {
    "thumbnail_url": "https://i.pinimg.com/236x/15/0c/94/150c941b007e51d61268f5672cd94e9a.jpg",
    "pin_url": "https://kr.pinterest.com/pin/1548181165889273/"
  },
  {
    "thumbnail_url": "https://i.pinimg.com/236x/6e/57/b6/6e57b61cb63766789a6776481b73cc22.jpg",
    "pin_url": "https://kr.pinterest.com/pin/15129348743892539/"
  }
]